<Properties StartupConfiguration="{2FA9CBA6-7A9C-4739-B4F0-52D996AB8F21}|Default">
  <MonoDevelop.Ide.DebuggingService.PinnedWatches />
  <MonoDevelop.Ide.Workspace ActiveConfiguration="Debug" />
  <MonoDevelop.Ide.ItemProperties.CourseWork PreferredExecutionTarget="MonoDevelop.Default" />
  <MonoDevelop.Ide.Workbench ActiveDocument="Controllers/HistoryController.cs">
    <Files>
      <File FileName=".gitattributes" Line="1" Column="1" />
      <File FileName="MockProduct.cs" Line="1" Column="1" />
      <File FileName="Controllers/HistoryController.cs" Line="1" Column="1" />
    </Files>
    <Pads>
      <Pad Id="ProjectPad">
        <State name="__root__">
          <Node name="CourseWork" expanded="True">
            <Node name="CourseWork" expanded="True">
              <Node name="Controllers" expanded="True">
                <Node name="HistoryController.cs" selected="True" />
              </Node>
            </Node>
          </Node>
        </State>
      </Pad>
      <Pad Id="MonoDevelop.Debugger.WatchPad">
        <State />
      </Pad>
    </Pads>
  </MonoDevelop.Ide.Workbench>
  <MonoDevelop.Ide.DebuggingService.Breakpoints>
    <BreakpointStore />
  </MonoDevelop.Ide.DebuggingService.Breakpoints>
  <MultiItemStartupConfigurations />
</Properties>